walls.py
walls-0.1.2.dist-info/DESCRIPTION.rst
walls-0.1.2.dist-info/METADATA
walls-0.1.2.dist-info/RECORD
walls-0.1.2.dist-info/WHEEL
walls-0.1.2.dist-info/entry_points.txt
walls-0.1.2.dist-info/metadata.json
walls-0.1.2.dist-info/top_level.txt
