Metadata-Version: 2.0
Name: walls
Version: 0.1.2
Summary: Random Flickr wallpapers.
Home-page: https://github.com/nickfrostatx/walls
Author: Nick Frost
Author-email: nickfrostatx@gmail.com
License: MIT
Keywords: walls
Platform: UNKNOWN
Classifier: Development Status :: 2 - Pre-Alpha
Classifier: Intended Audience :: Developers
Classifier: License :: OSI Approved :: MIT License
Classifier: Programming Language :: Python :: 2
Classifier: Programming Language :: Python :: 2.7
Classifier: Programming Language :: Python :: 3
Classifier: Programming Language :: Python :: 3.3
Classifier: Programming Language :: Python :: 3.4
Classifier: Programming Language :: Python :: 3.5
Classifier: Programming Language :: Python :: Implementation :: CPython
Classifier: Programming Language :: Python :: Implementation :: PyPy
Requires-Dist: flickrapi
Requires-Dist: requests
Provides-Extra: testing
Requires-Dist: pytest; extra == 'testing'
Requires-Dist: pytest-cov; extra == 'testing'
Requires-Dist: pytest-pep257; extra == 'testing'
Requires-Dist: pytest-pep8; extra == 'testing'
